simpleJDB/__init__.py
simpleJDB/functions.py
simpleJDB-0.1.3.dist-info/LICENSE
simpleJDB-0.1.3.dist-info/METADATA
simpleJDB-0.1.3.dist-info/WHEEL
simpleJDB-0.1.3.dist-info/top_level.txt
simpleJDB-0.1.3.dist-info/RECORD
