Metadata-Version: 2.1
Name: simpleJDB
Version: 0.1.3
Summary: jsonDB - A Python library for json-based databases with thread-safety, staging/commit and easy-to-use API.
Home-page: https://github.com/Milkman337/simpleJDB/tree/master/simpleJDB
Author: Jan
Author-email: krisellp9@gmail.com
Project-URL: Bug Tracker, https://github.com/Milkman337/simpleJDB/issues
Classifier: Programming Language :: Python :: 3
Classifier: License :: OSI Approved :: MIT License
Classifier: Operating System :: OS Independent
Requires-Python: >=3.6
License-File: LICENSE
